[
    {
        "INCIDENT_DATE": "1-Feb-03", 
        "STATE": "FL", 
        "INCIDENT_YEAR": "2003", 
        "AIRPORT": "SARASOTA-BRADENTON", 
        "INCIDENT_MONTH": "2", 
        "AIRPORT_ID": "KSRQ", 
        "TIME": "", 
        "INDEX_NR": "213180"
    }, 
    {
        "INCIDENT_DATE": "1-Feb-03", 
        "STATE": "TX", 
        "INCIDENT_YEAR": "2003", 
        "AIRPORT": "DALLAS/FORT WORTH INTL ARPT", 
        "INCIDENT_MONTH": "2", 
        "AIRPORT_ID": "KDFW", 
        "TIME": "949", 
        "INDEX_NR": "214364"
    }, 
    {
        "INCIDENT_DATE": "1-Feb-03", 
        "STATE": "CA", 
        "INCIDENT_YEAR": "2003", 
        "AIRPORT": "BOB HOPE ARPT", 
        "INCIDENT_MONTH": "2", 
        "AIRPORT_ID": "KBUR", 
        "TIME": "1657", 
        "INDEX_NR": "215407"
    }, 
    {
        "INCIDENT_DATE": "1-Feb-03", 
        "STATE": "FL", 
        "INCIDENT_YEAR": "2003", 
        "AIRPORT": "MIAMI INTL", 
        "INCIDENT_MONTH": "2", 
        "AIRPORT_ID": "KMIA", 
        "TIME": "1310", 
        "INDEX_NR": "215408"
    }, 
    {
        "INCIDENT_DATE": "1-Feb-03", 
        "STATE": "CA", 
        "INCIDENT_YEAR": "2003", 
        "AIRPORT": "METRO OAKLAND INTL", 
        "INCIDENT_MONTH": "2", 
        "AIRPORT_ID": "KOAK", 
        "TIME": "1812", 
        "INDEX_NR": "218766"
    }, 
    {
        "INCIDENT_DATE": "1-Feb-03", 
        "STATE": "TX", 
        "INCIDENT_YEAR": "2003", 
        "AIRPORT": "DALLAS/FORT WORTH INTL ARPT", 
        "INCIDENT_MONTH": "2", 
        "AIRPORT_ID": "KDFW", 
        "TIME": "", 
        "INDEX_NR": "219729"
    }, 
    {
        "INCIDENT_DATE": "1-Feb-03", 
        "STATE": "N/A", 
        "INCIDENT_YEAR": "2003", 
        "AIRPORT": "PUNTA CANA INTL", 
        "INCIDENT_MONTH": "2", 
        "AIRPORT_ID": "MDPC", 
        "TIME": "", 
        "INDEX_NR": "220436"
    }, 
    {
        "INCIDENT_DATE": "1-Feb-03", 
        "STATE": "IL", 
        "INCIDENT_YEAR": "2003", 
        "AIRPORT": "CHICAGO O'HARE INTL ARPT", 
        "INCIDENT_MONTH": "2", 
        "AIRPORT_ID": "KORD", 
        "TIME": "", 
        "INDEX_NR": "232446"
    }, 
    {
        "INCIDENT_DATE": "2-Feb-03", 
        "STATE": "SC", 
        "INCIDENT_YEAR": "2003", 
        "AIRPORT": "CHARLESTON AFB/INTL ARPT", 
        "INCIDENT_MONTH": "2", 
        "AIRPORT_ID": "KCHS", 
        "TIME": "1215", 
        "INDEX_NR": "4182"
    }, 
    {
        "INCIDENT_DATE": "2-Feb-03", 
        "STATE": "N/A", 
        "INCIDENT_YEAR": "2003", 
        "AIRPORT": "UNKNOWN", 
        "INCIDENT_MONTH": "2", 
        "AIRPORT_ID": "UNK", 
        "TIME": "", 
        "INDEX_NR": "214448"
    }, 
    {
        "INCIDENT_DATE": "2-Feb-03", 
        "STATE": "OR", 
        "INCIDENT_YEAR": "2003", 
        "AIRPORT": "MAHLON SWEET FLD", 
        "INCIDENT_MONTH": "2", 
        "AIRPORT_ID": "KEUG", 
        "TIME": "1800", 
        "INDEX_NR": "215888"
    }, 
    {
        "INCIDENT_DATE": "2-Feb-03", 
        "STATE": "CA", 
        "INCIDENT_YEAR": "2003", 
        "AIRPORT": "SACRAMENTO INTL", 
        "INCIDENT_MONTH": "2", 
        "AIRPORT_ID": "KSMF", 
        "TIME": "", 
        "INDEX_NR": "216398"
    }, 
    {
        "INCIDENT_DATE": "2-Feb-03", 
        "STATE": "CA", 
        "INCIDENT_YEAR": "2003", 
        "AIRPORT": "SAN DIEGO INTL", 
        "INCIDENT_MONTH": "2", 
        "AIRPORT_ID": "KSAN", 
        "TIME": "", 
        "INDEX_NR": "217339"
    }, 
    {
        "INCIDENT_DATE": "2-Feb-03", 
        "STATE": "CA", 
        "INCIDENT_YEAR": "2003", 
        "AIRPORT": "SAN FRANCISCO INTL ARPT", 
        "INCIDENT_MONTH": "2", 
        "AIRPORT_ID": "KSFO", 
        "TIME": "", 
        "INDEX_NR": "219549"
    }, 
    {
        "INCIDENT_DATE": "2-Feb-03", 
        "STATE": "TX", 
        "INCIDENT_YEAR": "2003", 
        "AIRPORT": "DALLAS LOVE FIELD ARPT", 
        "INCIDENT_MONTH": "2", 
        "AIRPORT_ID": "KDAL", 
        "TIME": "825", 
        "INDEX_NR": "219688"
    }, 
    {
        "INCIDENT_DATE": "2-Feb-03", 
        "STATE": "HI", 
        "INCIDENT_YEAR": "2003", 
        "AIRPORT": "KALAELOA ARPT JOHN RODGERS FIELD", 
        "INCIDENT_MONTH": "2", 
        "AIRPORT_ID": "PHJR", 
        "TIME": "", 
        "INDEX_NR": "220336"
    }, 
    {
        "INCIDENT_DATE": "3-Feb-03", 
        "STATE": "FL", 
        "INCIDENT_YEAR": "2003", 
        "AIRPORT": "ORLANDO INTL", 
        "INCIDENT_MONTH": "2", 
        "AIRPORT_ID": "KMCO", 
        "TIME": "", 
        "INDEX_NR": "214365"
    }, 
    {
        "INCIDENT_DATE": "3-Feb-03", 
        "STATE": "TX", 
        "INCIDENT_YEAR": "2003", 
        "AIRPORT": "DALLAS LOVE FIELD ARPT", 
        "INCIDENT_MONTH": "2", 
        "AIRPORT_ID": "KDAL", 
        "TIME": "", 
        "INDEX_NR": "215043"
    }, 
    {
        "INCIDENT_DATE": "3-Feb-03", 
        "STATE": "NY", 
        "INCIDENT_YEAR": "2003", 
        "AIRPORT": "JOHN F KENNEDY INTL", 
        "INCIDENT_MONTH": "2", 
        "AIRPORT_ID": "KJFK", 
        "TIME": "", 
        "INDEX_NR": "216367"
    }, 
    {
        "INCIDENT_DATE": "3-Feb-03", 
        "STATE": "NY", 
        "INCIDENT_YEAR": "2003", 
        "AIRPORT": "JOHN F KENNEDY INTL", 
        "INCIDENT_MONTH": "2", 
        "AIRPORT_ID": "KJFK", 
        "TIME": "1228", 
        "INDEX_NR": "216928"
    }, 
    {
        "INCIDENT_DATE": "3-Feb-03", 
        "STATE": "NY", 
        "INCIDENT_YEAR": "2003", 
        "AIRPORT": "JOHN F KENNEDY INTL", 
        "INCIDENT_MONTH": "2", 
        "AIRPORT_ID": "KJFK", 
        "TIME": "", 
        "INDEX_NR": "217139"
    }, 
    {
        "INCIDENT_DATE": "3-Feb-03", 
        "STATE": "NY", 
        "INCIDENT_YEAR": "2003", 
        "AIRPORT": "JOHN F KENNEDY INTL", 
        "INCIDENT_MONTH": "2", 
        "AIRPORT_ID": "KJFK", 
        "TIME": "", 
        "INDEX_NR": "218159"
    }, 
    {
        "INCIDENT_DATE": "3-Feb-03", 
        "STATE": "DC", 
        "INCIDENT_YEAR": "2003", 
        "AIRPORT": "WASHINGTON DULLES INTL ARPT", 
        "INCIDENT_MONTH": "2", 
        "AIRPORT_ID": "KIAD", 
        "TIME": "1300", 
        "INDEX_NR": "220344"
    }, 
    {
        "INCIDENT_DATE": "3-Feb-03", 
        "STATE": "CA", 
        "INCIDENT_YEAR": "2003", 
        "AIRPORT": "LOS ANGELES INTL", 
        "INCIDENT_MONTH": "2", 
        "AIRPORT_ID": "KLAX", 
        "TIME": "", 
        "INDEX_NR": "221356"
    }, 
    {
        "INCIDENT_DATE": "3-Feb-03", 
        "STATE": "GA", 
        "INCIDENT_YEAR": "2003", 
        "AIRPORT": "ATLANTA INTL", 
        "INCIDENT_MONTH": "2", 
        "AIRPORT_ID": "KATL", 
        "TIME": "", 
        "INDEX_NR": "228040"
    }, 
    {
        "INCIDENT_DATE": "4-Feb-03", 
        "STATE": "OH", 
        "INCIDENT_YEAR": "2003", 
        "AIRPORT": "AIRBORNE AIRPARK", 
        "INCIDENT_MONTH": "2", 
        "AIRPORT_ID": "KILN", 
        "TIME": "840", 
        "INDEX_NR": "215272"
    }, 
    {
        "INCIDENT_DATE": "4-Feb-03", 
        "STATE": "N/A", 
        "INCIDENT_YEAR": "2003", 
        "AIRPORT": "UNKNOWN", 
        "INCIDENT_MONTH": "2", 
        "AIRPORT_ID": "UNK", 
        "TIME": "", 
        "INDEX_NR": "216671"
    }, 
    {
        "INCIDENT_DATE": "4-Feb-03", 
        "STATE": "DC", 
        "INCIDENT_YEAR": "2003", 
        "AIRPORT": "WASHINGTON DULLES INTL ARPT", 
        "INCIDENT_MONTH": "2", 
        "AIRPORT_ID": "KIAD", 
        "TIME": "900", 
        "INDEX_NR": "216880"
    }, 
    {
        "INCIDENT_DATE": "4-Feb-03", 
        "STATE": "AZ", 
        "INCIDENT_YEAR": "2003", 
        "AIRPORT": "PHOENIX SKY HARBOR", 
        "INCIDENT_MONTH": "2", 
        "AIRPORT_ID": "KPHX", 
        "TIME": "", 
        "INDEX_NR": "216881"
    }, 
    {
        "INCIDENT_DATE": "4-Feb-03", 
        "STATE": "FL", 
        "INCIDENT_YEAR": "2003", 
        "AIRPORT": "ST AUGUSTINE", 
        "INCIDENT_MONTH": "2", 
        "AIRPORT_ID": "KSGJ", 
        "TIME": "1201", 
        "INDEX_NR": "218288"
    }, 
    {
        "INCIDENT_DATE": "4-Feb-03", 
        "STATE": "N/A", 
        "INCIDENT_YEAR": "2003", 
        "AIRPORT": "MINISTRO PISTARINI", 
        "INCIDENT_MONTH": "2", 
        "AIRPORT_ID": "SAEZ", 
        "TIME": "", 
        "INDEX_NR": "218467"
    }, 
    {
        "INCIDENT_DATE": "4-Feb-03", 
        "STATE": "IL", 
        "INCIDENT_YEAR": "2003", 
        "AIRPORT": "QUAD CITY ARPT", 
        "INCIDENT_MONTH": "2", 
        "AIRPORT_ID": "KMLI", 
        "TIME": "638", 
        "INDEX_NR": "218468"
    }, 
    {
        "INCIDENT_DATE": "4-Feb-03", 
        "STATE": "NY", 
        "INCIDENT_YEAR": "2003", 
        "AIRPORT": "JOHN F KENNEDY INTL", 
        "INCIDENT_MONTH": "2", 
        "AIRPORT_ID": "KJFK", 
        "TIME": "", 
        "INDEX_NR": "218532"
    }, 
    {
        "INCIDENT_DATE": "5-Feb-03", 
        "STATE": "SC", 
        "INCIDENT_YEAR": "2003", 
        "AIRPORT": "CHARLESTON AFB/INTL ARPT", 
        "INCIDENT_MONTH": "2", 
        "AIRPORT_ID": "KCHS", 
        "TIME": "2000", 
        "INDEX_NR": "214425"
    }, 
    {
        "INCIDENT_DATE": "5-Feb-03", 
        "STATE": "TX", 
        "INCIDENT_YEAR": "2003", 
        "AIRPORT": "DALLAS/FORT WORTH INTL ARPT", 
        "INCIDENT_MONTH": "2", 
        "AIRPORT_ID": "KDFW", 
        "TIME": "", 
        "INDEX_NR": "220720"
    }, 
    {
        "INCIDENT_DATE": "6-Feb-03", 
        "STATE": "NY", 
        "INCIDENT_YEAR": "2003", 
        "AIRPORT": "JOHN F KENNEDY INTL", 
        "INCIDENT_MONTH": "2", 
        "AIRPORT_ID": "KJFK", 
        "TIME": "", 
        "INDEX_NR": "216438"
    }, 
    {
        "INCIDENT_DATE": "6-Feb-03", 
        "STATE": "WA", 
        "INCIDENT_YEAR": "2003", 
        "AIRPORT": "SEATTLE-TACOMA INTL", 
        "INCIDENT_MONTH": "2", 
        "AIRPORT_ID": "KSEA", 
        "TIME": "", 
        "INDEX_NR": "216509"
    }, 
    {
        "INCIDENT_DATE": "6-Feb-03", 
        "STATE": "HI", 
        "INCIDENT_YEAR": "2003", 
        "AIRPORT": "KAPALUA ARPT", 
        "INCIDENT_MONTH": "2", 
        "AIRPORT_ID": "PHJH", 
        "TIME": "", 
        "INDEX_NR": "218749"
    }, 
    {
        "INCIDENT_DATE": "6-Feb-03", 
        "STATE": "NC", 
        "INCIDENT_YEAR": "2003", 
        "AIRPORT": "CHARLOTTE/DOUGLAS INTL ARPT", 
        "INCIDENT_MONTH": "2", 
        "AIRPORT_ID": "KCLT", 
        "TIME": "1453", 
        "INDEX_NR": "218826"
    }, 
    {
        "INCIDENT_DATE": "6-Feb-03", 
        "STATE": "HI", 
        "INCIDENT_YEAR": "2003", 
        "AIRPORT": "LIHUE ARPT", 
        "INCIDENT_MONTH": "2", 
        "AIRPORT_ID": "PHLI", 
        "TIME": "954", 
        "INDEX_NR": "219234"
    }, 
    {
        "INCIDENT_DATE": "6-Feb-03", 
        "STATE": "VA", 
        "INCIDENT_YEAR": "2003", 
        "AIRPORT": "LYNCHBURG REGIONAL", 
        "INCIDENT_MONTH": "2", 
        "AIRPORT_ID": "KLYH", 
        "TIME": "181", 
        "INDEX_NR": "219891"
    }, 
    {
        "INCIDENT_DATE": "6-Feb-03", 
        "STATE": "FL", 
        "INCIDENT_YEAR": "2003", 
        "AIRPORT": "NAPLES MUNICIPAL", 
        "INCIDENT_MONTH": "2", 
        "AIRPORT_ID": "KAPF", 
        "TIME": "", 
        "INDEX_NR": "220217"
    }, 
    {
        "INCIDENT_DATE": "6-Feb-03", 
        "STATE": "N/A", 
        "INCIDENT_YEAR": "2003", 
        "AIRPORT": "UNKNOWN", 
        "INCIDENT_MONTH": "2", 
        "AIRPORT_ID": "UNK", 
        "TIME": "", 
        "INDEX_NR": "221148"
    }, 
    {
        "INCIDENT_DATE": "6-Feb-03", 
        "STATE": "NY", 
        "INCIDENT_YEAR": "2003", 
        "AIRPORT": "JOHN F KENNEDY INTL", 
        "INCIDENT_MONTH": "2", 
        "AIRPORT_ID": "KJFK", 
        "TIME": "830", 
        "INDEX_NR": "222255"
    }, 
    {
        "INCIDENT_DATE": "7-Feb-03", 
        "STATE": "FL", 
        "INCIDENT_YEAR": "2003", 
        "AIRPORT": "EGLIN AFB/NW FLORIDA REGIONAL ARPT", 
        "INCIDENT_MONTH": "2", 
        "AIRPORT_ID": "KVPS", 
        "TIME": "", 
        "INDEX_NR": "6934"
    }, 
    {
        "INCIDENT_DATE": "7-Feb-03", 
        "STATE": "MA", 
        "INCIDENT_YEAR": "2003", 
        "AIRPORT": "LOGAN INTL", 
        "INCIDENT_MONTH": "2", 
        "AIRPORT_ID": "KBOS", 
        "TIME": "", 
        "INDEX_NR": "219315"
    }, 
    {
        "INCIDENT_DATE": "7-Feb-03", 
        "STATE": "PI", 
        "INCIDENT_YEAR": "2003", 
        "AIRPORT": "PAGO PAGO INTL", 
        "INCIDENT_MONTH": "2", 
        "AIRPORT_ID": "NSTU", 
        "TIME": "910", 
        "INDEX_NR": "220556"
    }, 
    {
        "INCIDENT_DATE": "7-Feb-03", 
        "STATE": "CA", 
        "INCIDENT_YEAR": "2003", 
        "AIRPORT": "SAN CARLOS ARPT", 
        "INCIDENT_MONTH": "2", 
        "AIRPORT_ID": "KSQL", 
        "TIME": "1030", 
        "INDEX_NR": "221137"
    }, 
    {
        "INCIDENT_DATE": "7-Feb-03", 
        "STATE": "FL", 
        "INCIDENT_YEAR": "2003", 
        "AIRPORT": "JACKSONVILLE INTL", 
        "INCIDENT_MONTH": "2", 
        "AIRPORT_ID": "KJAX", 
        "TIME": "", 
        "INDEX_NR": "221320"
    }, 
    {
        "INCIDENT_DATE": "7-Feb-03", 
        "STATE": "CA", 
        "INCIDENT_YEAR": "2003", 
        "AIRPORT": "METRO OAKLAND INTL", 
        "INCIDENT_MONTH": "2", 
        "AIRPORT_ID": "KOAK", 
        "TIME": "1955", 
        "INDEX_NR": "221795"
    }, 
    {
        "INCIDENT_DATE": "8-Feb-03", 
        "STATE": "TX", 
        "INCIDENT_YEAR": "2003", 
        "AIRPORT": "ABILENE REGIONAL ARPT", 
        "INCIDENT_MONTH": "2", 
        "AIRPORT_ID": "KABI", 
        "TIME": "1725", 
        "INDEX_NR": "7542"
    }, 
    {
        "INCIDENT_DATE": "8-Feb-03", 
        "STATE": "NJ", 
        "INCIDENT_YEAR": "2003", 
        "AIRPORT": "TETERBORO AIRPORT", 
        "INCIDENT_MONTH": "2", 
        "AIRPORT_ID": "KTEB", 
        "TIME": "2010", 
        "INDEX_NR": "218320"
    }, 
    {
        "INCIDENT_DATE": "8-Feb-03", 
        "STATE": "CA", 
        "INCIDENT_YEAR": "2003", 
        "AIRPORT": "METRO OAKLAND INTL", 
        "INCIDENT_MONTH": "2", 
        "AIRPORT_ID": "KOAK", 
        "TIME": "2015", 
        "INDEX_NR": "218469"
    }, 
    {
        "INCIDENT_DATE": "8-Feb-03", 
        "STATE": "HI", 
        "INCIDENT_YEAR": "2003", 
        "AIRPORT": "LIHUE ARPT", 
        "INCIDENT_MONTH": "2", 
        "AIRPORT_ID": "PHLI", 
        "TIME": "1728", 
        "INDEX_NR": "218470"
    }, 
    {
        "INCIDENT_DATE": "8-Feb-03", 
        "STATE": "CA", 
        "INCIDENT_YEAR": "2003", 
        "AIRPORT": "SANTA BARBARA MUNICIPAL", 
        "INCIDENT_MONTH": "2", 
        "AIRPORT_ID": "KSBA", 
        "TIME": "842", 
        "INDEX_NR": "219316"
    }, 
    {
        "INCIDENT_DATE": "8-Feb-03", 
        "STATE": "MA", 
        "INCIDENT_YEAR": "2003", 
        "AIRPORT": "LOGAN INTL", 
        "INCIDENT_MONTH": "2", 
        "AIRPORT_ID": "KBOS", 
        "TIME": "", 
        "INDEX_NR": "220702"
    }, 
    {
        "INCIDENT_DATE": "8-Feb-03", 
        "STATE": "AZ", 
        "INCIDENT_YEAR": "2003", 
        "AIRPORT": "TUCSON INTL", 
        "INCIDENT_MONTH": "2", 
        "AIRPORT_ID": "KTUS", 
        "TIME": "", 
        "INDEX_NR": "221784"
    }, 
    {
        "INCIDENT_DATE": "9-Feb-03", 
        "STATE": "NY", 
        "INCIDENT_YEAR": "2003", 
        "AIRPORT": "JOHN F KENNEDY INTL", 
        "INCIDENT_MONTH": "2", 
        "AIRPORT_ID": "KJFK", 
        "TIME": "", 
        "INDEX_NR": "220682"
    }, 
    {
        "INCIDENT_DATE": "9-Feb-03", 
        "STATE": "WA", 
        "INCIDENT_YEAR": "2003", 
        "AIRPORT": "SEATTLE-TACOMA INTL", 
        "INCIDENT_MONTH": "2", 
        "AIRPORT_ID": "KSEA", 
        "TIME": "", 
        "INDEX_NR": "221692"
    }, 
    {
        "INCIDENT_DATE": "9-Feb-03", 
        "STATE": "CA", 
        "INCIDENT_YEAR": "2003", 
        "AIRPORT": "METRO OAKLAND INTL", 
        "INCIDENT_MONTH": "2", 
        "AIRPORT_ID": "KOAK", 
        "TIME": "", 
        "INDEX_NR": "221866"
    }, 
    {
        "INCIDENT_DATE": "10-Feb-03", 
        "STATE": "TX", 
        "INCIDENT_YEAR": "2003", 
        "AIRPORT": "FORT WORTH ALLIANCE", 
        "INCIDENT_MONTH": "2", 
        "AIRPORT_ID": "KAFW", 
        "TIME": "1645", 
        "INDEX_NR": "7699"
    }, 
    {
        "INCIDENT_DATE": "10-Feb-03", 
        "STATE": "FL", 
        "INCIDENT_YEAR": "2003", 
        "AIRPORT": "TAMPA INTL", 
        "INCIDENT_MONTH": "2", 
        "AIRPORT_ID": "KTPA", 
        "TIME": "", 
        "INDEX_NR": "217756"
    }, 
    {
        "INCIDENT_DATE": "10-Feb-03", 
        "STATE": "CA", 
        "INCIDENT_YEAR": "2003", 
        "AIRPORT": "SANTA BARBARA MUNICIPAL", 
        "INCIDENT_MONTH": "2", 
        "AIRPORT_ID": "KSBA", 
        "TIME": "", 
        "INDEX_NR": "218405"
    }, 
    {
        "INCIDENT_DATE": "10-Feb-03", 
        "STATE": "MI", 
        "INCIDENT_YEAR": "2003", 
        "AIRPORT": "KALAMAZOO/BATTLE CREEK INTL", 
        "INCIDENT_MONTH": "2", 
        "AIRPORT_ID": "KAZO", 
        "TIME": "1235", 
        "INDEX_NR": "225936"
    }, 
    {
        "INCIDENT_DATE": "11-Feb-03", 
        "STATE": "AR", 
        "INCIDENT_YEAR": "2003", 
        "AIRPORT": "ADAMS FIELD ARPT", 
        "INCIDENT_MONTH": "2", 
        "AIRPORT_ID": "KLIT", 
        "TIME": "", 
        "INDEX_NR": "5991"
    }, 
    {
        "INCIDENT_DATE": "11-Feb-03", 
        "STATE": "KY", 
        "INCIDENT_YEAR": "2003", 
        "AIRPORT": "LOUISVILLE INTL ARPT", 
        "INCIDENT_MONTH": "2", 
        "AIRPORT_ID": "KSDF", 
        "TIME": "", 
        "INDEX_NR": "212577"
    }, 
    {
        "INCIDENT_DATE": "11-Feb-03", 
        "STATE": "KY", 
        "INCIDENT_YEAR": "2003", 
        "AIRPORT": "LOUISVILLE INTL ARPT", 
        "INCIDENT_MONTH": "2", 
        "AIRPORT_ID": "KSDF", 
        "TIME": "", 
        "INDEX_NR": "213150"
    }, 
    {
        "INCIDENT_DATE": "11-Feb-03", 
        "STATE": "KY", 
        "INCIDENT_YEAR": "2003", 
        "AIRPORT": "LOUISVILLE INTL ARPT", 
        "INCIDENT_MONTH": "2", 
        "AIRPORT_ID": "KSDF", 
        "TIME": "", 
        "INDEX_NR": "213151"
    }, 
    {
        "INCIDENT_DATE": "11-Feb-03", 
        "STATE": "NC", 
        "INCIDENT_YEAR": "2003", 
        "AIRPORT": "RALEIGH-DURHAM INTL", 
        "INCIDENT_MONTH": "2", 
        "AIRPORT_ID": "KRDU", 
        "TIME": "1617", 
        "INDEX_NR": "214223"
    }, 
    {
        "INCIDENT_DATE": "11-Feb-03", 
        "STATE": "NY", 
        "INCIDENT_YEAR": "2003", 
        "AIRPORT": "JOHN F KENNEDY INTL", 
        "INCIDENT_MONTH": "2", 
        "AIRPORT_ID": "KJFK", 
        "TIME": "", 
        "INDEX_NR": "214766"
    }, 
    {
        "INCIDENT_DATE": "11-Feb-03", 
        "STATE": "KS", 
        "INCIDENT_YEAR": "2003", 
        "AIRPORT": "ATKINSON MUNICIPAL", 
        "INCIDENT_MONTH": "2", 
        "AIRPORT_ID": "KPTS", 
        "TIME": "2030", 
        "INDEX_NR": "216248"
    }, 
    {
        "INCIDENT_DATE": "11-Feb-03", 
        "STATE": "N/A", 
        "INCIDENT_YEAR": "2003", 
        "AIRPORT": "UNKNOWN", 
        "INCIDENT_MONTH": "2", 
        "AIRPORT_ID": "UNK", 
        "TIME": "", 
        "INDEX_NR": "221393"
    }, 
    {
        "INCIDENT_DATE": "12-Feb-03", 
        "STATE": "TX", 
        "INCIDENT_YEAR": "2003", 
        "AIRPORT": "SHEPPARD AIR FORCE BASE", 
        "INCIDENT_MONTH": "2", 
        "AIRPORT_ID": "KSPS", 
        "TIME": "1000", 
        "INDEX_NR": "6935"
    }, 
    {
        "INCIDENT_DATE": "12-Feb-03", 
        "STATE": "FL", 
        "INCIDENT_YEAR": "2003", 
        "AIRPORT": "ORLANDO INTL", 
        "INCIDENT_MONTH": "2", 
        "AIRPORT_ID": "KMCO", 
        "TIME": "", 
        "INDEX_NR": "218649"
    }, 
    {
        "INCIDENT_DATE": "12-Feb-03", 
        "STATE": "N/A", 
        "INCIDENT_YEAR": "2003", 
        "AIRPORT": "UNKNOWN", 
        "INCIDENT_MONTH": "2", 
        "AIRPORT_ID": "UNK", 
        "TIME": "", 
        "INDEX_NR": "219411"
    }, 
    {
        "INCIDENT_DATE": "12-Feb-03", 
        "STATE": "N/A", 
        "INCIDENT_YEAR": "2003", 
        "AIRPORT": "MINISTRO PISTARINI", 
        "INCIDENT_MONTH": "2", 
        "AIRPORT_ID": "SAEZ", 
        "TIME": "", 
        "INDEX_NR": "219412"
    }, 
    {
        "INCIDENT_DATE": "12-Feb-03", 
        "STATE": "CA", 
        "INCIDENT_YEAR": "2003", 
        "AIRPORT": "SAN DIEGO INTL", 
        "INCIDENT_MONTH": "2", 
        "AIRPORT_ID": "KSAN", 
        "TIME": "1015", 
        "INDEX_NR": "220451"
    }, 
    {
        "INCIDENT_DATE": "12-Feb-03", 
        "STATE": "NY", 
        "INCIDENT_YEAR": "2003", 
        "AIRPORT": "LAGUARDIA NY", 
        "INCIDENT_MONTH": "2", 
        "AIRPORT_ID": "KLGA", 
        "TIME": "2005", 
        "INDEX_NR": "220622"
    }, 
    {
        "INCIDENT_DATE": "13-Feb-03", 
        "STATE": "TX", 
        "INCIDENT_YEAR": "2003", 
        "AIRPORT": "SHEPPARD AIR FORCE BASE", 
        "INCIDENT_MONTH": "2", 
        "AIRPORT_ID": "KSPS", 
        "TIME": "", 
        "INDEX_NR": "6936"
    }, 
    {
        "INCIDENT_DATE": "13-Feb-03", 
        "STATE": "CA", 
        "INCIDENT_YEAR": "2003", 
        "AIRPORT": "LOS ANGELES INTL", 
        "INCIDENT_MONTH": "2", 
        "AIRPORT_ID": "KLAX", 
        "TIME": "", 
        "INDEX_NR": "214723"
    }, 
    {
        "INCIDENT_DATE": "13-Feb-03", 
        "STATE": "CA", 
        "INCIDENT_YEAR": "2003", 
        "AIRPORT": "SANTA BARBARA MUNICIPAL", 
        "INCIDENT_MONTH": "2", 
        "AIRPORT_ID": "KSBA", 
        "TIME": "1132", 
        "INDEX_NR": "218173"
    }, 
    {
        "INCIDENT_DATE": "13-Feb-03", 
        "STATE": "WA", 
        "INCIDENT_YEAR": "2003", 
        "AIRPORT": "SNOHOMISH CO (PAINE FIELD)", 
        "INCIDENT_MONTH": "2", 
        "AIRPORT_ID": "KPAE", 
        "TIME": "", 
        "INDEX_NR": "218482"
    }, 
    {
        "INCIDENT_DATE": "13-Feb-03", 
        "STATE": "AL", 
        "INCIDENT_YEAR": "2003", 
        "AIRPORT": "UNKNOWN", 
        "INCIDENT_MONTH": "2", 
        "AIRPORT_ID": "UNK", 
        "TIME": "2230", 
        "INDEX_NR": "222047"
    }, 
    {
        "INCIDENT_DATE": "14-Feb-03", 
        "STATE": "CA", 
        "INCIDENT_YEAR": "2003", 
        "AIRPORT": "MINETA SAN JOSE INTL", 
        "INCIDENT_MONTH": "2", 
        "AIRPORT_ID": "KSJC", 
        "TIME": "", 
        "INDEX_NR": "214001"
    }, 
    {
        "INCIDENT_DATE": "14-Feb-03", 
        "STATE": "FL", 
        "INCIDENT_YEAR": "2003", 
        "AIRPORT": "JACKSONVILLE INTL", 
        "INCIDENT_MONTH": "2", 
        "AIRPORT_ID": "KJAX", 
        "TIME": "", 
        "INDEX_NR": "214875"
    }, 
    {
        "INCIDENT_DATE": "14-Feb-03", 
        "STATE": "FL", 
        "INCIDENT_YEAR": "2003", 
        "AIRPORT": "SARASOTA-BRADENTON", 
        "INCIDENT_MONTH": "2", 
        "AIRPORT_ID": "KSRQ", 
        "TIME": "", 
        "INDEX_NR": "220934"
    }, 
    {
        "INCIDENT_DATE": "14-Feb-03", 
        "STATE": "N/A", 
        "INCIDENT_YEAR": "2003", 
        "AIRPORT": "MINISTRO PISTARINI", 
        "INCIDENT_MONTH": "2", 
        "AIRPORT_ID": "SAEZ", 
        "TIME": "", 
        "INDEX_NR": "221319"
    }, 
    {
        "INCIDENT_DATE": "15-Feb-03", 
        "STATE": "CA", 
        "INCIDENT_YEAR": "2003", 
        "AIRPORT": "SAN FRANCISCO INTL ARPT", 
        "INCIDENT_MONTH": "2", 
        "AIRPORT_ID": "KSFO", 
        "TIME": "430", 
        "INDEX_NR": "214960"
    }, 
    {
        "INCIDENT_DATE": "15-Feb-03", 
        "STATE": "TX", 
        "INCIDENT_YEAR": "2003", 
        "AIRPORT": "HOUSTON-HOBBY", 
        "INCIDENT_MONTH": "2", 
        "AIRPORT_ID": "KHOU", 
        "TIME": "", 
        "INDEX_NR": "221044"
    }, 
    {
        "INCIDENT_DATE": "15-Feb-03", 
        "STATE": "FL", 
        "INCIDENT_YEAR": "2003", 
        "AIRPORT": "FORT LAUDERDALE EXECUTIVE ARPT", 
        "INCIDENT_MONTH": "2", 
        "AIRPORT_ID": "KFXE", 
        "TIME": "2256", 
        "INDEX_NR": "221691"
    }, 
    {
        "INCIDENT_DATE": "15-Feb-03", 
        "STATE": "N/A", 
        "INCIDENT_YEAR": "2003", 
        "AIRPORT": "UNKNOWN", 
        "INCIDENT_MONTH": "2", 
        "AIRPORT_ID": "UNK", 
        "TIME": "", 
        "INDEX_NR": "221843"
    }, 
    {
        "INCIDENT_DATE": "15-Feb-03", 
        "STATE": "PA", 
        "INCIDENT_YEAR": "2003", 
        "AIRPORT": "GREATER PITTSBURGH", 
        "INCIDENT_MONTH": "2", 
        "AIRPORT_ID": "KPIT", 
        "TIME": "1429", 
        "INDEX_NR": "222876"
    }, 
    {
        "INCIDENT_DATE": "16-Feb-03", 
        "STATE": "CA", 
        "INCIDENT_YEAR": "2003", 
        "AIRPORT": "BOB HOPE ARPT", 
        "INCIDENT_MONTH": "2", 
        "AIRPORT_ID": "KBUR", 
        "TIME": "", 
        "INDEX_NR": "211842"
    }, 
    {
        "INCIDENT_DATE": "16-Feb-03", 
        "STATE": "FL", 
        "INCIDENT_YEAR": "2003", 
        "AIRPORT": "JACKSONVILLE INTL", 
        "INCIDENT_MONTH": "2", 
        "AIRPORT_ID": "KJAX", 
        "TIME": "", 
        "INDEX_NR": "214201"
    }, 
    {
        "INCIDENT_DATE": "16-Feb-03", 
        "STATE": "N/A", 
        "INCIDENT_YEAR": "2003", 
        "AIRPORT": "SUBIC BAY INTL", 
        "INCIDENT_MONTH": "2", 
        "AIRPORT_ID": "RPLB", 
        "TIME": "2335", 
        "INDEX_NR": "214593"
    }, 
    {
        "INCIDENT_DATE": "16-Feb-03", 
        "STATE": "CA", 
        "INCIDENT_YEAR": "2003", 
        "AIRPORT": "SAN DIEGO INTL", 
        "INCIDENT_MONTH": "2", 
        "AIRPORT_ID": "KSAN", 
        "TIME": "", 
        "INDEX_NR": "215017"
    }, 
    {
        "INCIDENT_DATE": "16-Feb-03", 
        "STATE": "IL", 
        "INCIDENT_YEAR": "2003", 
        "AIRPORT": "CHICAGO O'HARE INTL ARPT", 
        "INCIDENT_MONTH": "2", 
        "AIRPORT_ID": "KORD", 
        "TIME": "1050", 
        "INDEX_NR": "215338"
    }, 
    {
        "INCIDENT_DATE": "16-Feb-03", 
        "STATE": "TN", 
        "INCIDENT_YEAR": "2003", 
        "AIRPORT": "TRI-CITIES REGIONAL TN/VA ARPT", 
        "INCIDENT_MONTH": "2", 
        "AIRPORT_ID": "KTRI", 
        "TIME": "1320", 
        "INDEX_NR": "216663"
    }, 
    {
        "INCIDENT_DATE": "16-Feb-03", 
        "STATE": "N/A", 
        "INCIDENT_YEAR": "2003", 
        "AIRPORT": "UNKNOWN", 
        "INCIDENT_MONTH": "2", 
        "AIRPORT_ID": "UNK", 
        "TIME": "", 
        "INDEX_NR": "216988"
    }, 
    {
        "INCIDENT_DATE": "16-Feb-03", 
        "STATE": "UT", 
        "INCIDENT_YEAR": "2003", 
        "AIRPORT": "SALT LAKE CITY INTL", 
        "INCIDENT_MONTH": "2", 
        "AIRPORT_ID": "KSLC", 
        "TIME": "1945", 
        "INDEX_NR": "217196"
    }, 
    {
        "INCIDENT_DATE": "16-Feb-03", 
        "STATE": "N/A", 
        "INCIDENT_YEAR": "2003", 
        "AIRPORT": "UNKNOWN", 
        "INCIDENT_MONTH": "2", 
        "AIRPORT_ID": "UNK", 
        "TIME": "", 
        "INDEX_NR": "222877"
    }, 
    {
        "INCIDENT_DATE": "17-Feb-03", 
        "STATE": "TX", 
        "INCIDENT_YEAR": "2003", 
        "AIRPORT": "ARCO HIGH ISLAND HELIPORT", 
        "INCIDENT_MONTH": "2", 
        "AIRPORT_ID": "15TE", 
        "TIME": "930", 
        "INDEX_NR": "213040"
    }, 
    {
        "INCIDENT_DATE": "17-Feb-03", 
        "STATE": "N/A", 
        "INCIDENT_YEAR": "2003", 
        "AIRPORT": "UNKNOWN", 
        "INCIDENT_MONTH": "2", 
        "AIRPORT_ID": "UNK", 
        "TIME": "", 
        "INDEX_NR": "214690"
    }, 
    {
        "INCIDENT_DATE": "17-Feb-03", 
        "STATE": "CA", 
        "INCIDENT_YEAR": "2003", 
        "AIRPORT": "METRO OAKLAND INTL", 
        "INCIDENT_MONTH": "2", 
        "AIRPORT_ID": "KOAK", 
        "TIME": "", 
        "INDEX_NR": "215300"
    }, 
    {
        "INCIDENT_DATE": "17-Feb-03", 
        "STATE": "CO", 
        "INCIDENT_YEAR": "2003", 
        "AIRPORT": "DENVER INTL AIRPORT", 
        "INCIDENT_MONTH": "2", 
        "AIRPORT_ID": "KDEN", 
        "TIME": "", 
        "INDEX_NR": "215427"
    }, 
    {
        "INCIDENT_DATE": "17-Feb-03", 
        "STATE": "HI", 
        "INCIDENT_YEAR": "2003", 
        "AIRPORT": "LIHUE ARPT", 
        "INCIDENT_MONTH": "2", 
        "AIRPORT_ID": "PHLI", 
        "TIME": "1226", 
        "INDEX_NR": "220766"
    }, 
    {
        "INCIDENT_DATE": "17-Feb-03", 
        "STATE": "N/A", 
        "INCIDENT_YEAR": "2003", 
        "AIRPORT": "UNKNOWN", 
        "INCIDENT_MONTH": "2", 
        "AIRPORT_ID": "UNK", 
        "TIME": "", 
        "INDEX_NR": "220767"
    }, 
    {
        "INCIDENT_DATE": "17-Feb-03", 
        "STATE": "TN", 
        "INCIDENT_YEAR": "2003", 
        "AIRPORT": "MEMPHIS INTL", 
        "INCIDENT_MONTH": "2", 
        "AIRPORT_ID": "KMEM", 
        "TIME": "", 
        "INDEX_NR": "222874"
    }, 
    {
        "INCIDENT_DATE": "18-Feb-03", 
        "STATE": "SC", 
        "INCIDENT_YEAR": "2003", 
        "AIRPORT": "CHARLESTON AFB/INTL ARPT", 
        "INCIDENT_MONTH": "2", 
        "AIRPORT_ID": "KCHS", 
        "TIME": "1700", 
        "INDEX_NR": "7698"
    }, 
    {
        "INCIDENT_DATE": "18-Feb-03", 
        "STATE": "CA", 
        "INCIDENT_YEAR": "2003", 
        "AIRPORT": "LOS ANGELES INTL", 
        "INCIDENT_MONTH": "2", 
        "AIRPORT_ID": "KLAX", 
        "TIME": "", 
        "INDEX_NR": "216032"
    }, 
    {
        "INCIDENT_DATE": "18-Feb-03", 
        "STATE": "FL", 
        "INCIDENT_YEAR": "2003", 
        "AIRPORT": "MIAMI INTL", 
        "INCIDENT_MONTH": "2", 
        "AIRPORT_ID": "KMIA", 
        "TIME": "", 
        "INDEX_NR": "216585"
    }, 
    {
        "INCIDENT_DATE": "18-Feb-03", 
        "STATE": "CA", 
        "INCIDENT_YEAR": "2003", 
        "AIRPORT": "LOS ANGELES INTL", 
        "INCIDENT_MONTH": "2", 
        "AIRPORT_ID": "KLAX", 
        "TIME": "", 
        "INDEX_NR": "217337"
    }, 
    {
        "INCIDENT_DATE": "18-Feb-03", 
        "STATE": "AR", 
        "INCIDENT_YEAR": "2003", 
        "AIRPORT": "ADAMS FIELD ARPT", 
        "INCIDENT_MONTH": "2", 
        "AIRPORT_ID": "KLIT", 
        "TIME": "2010", 
        "INDEX_NR": "217470"
    }, 
    {
        "INCIDENT_DATE": "18-Feb-03", 
        "STATE": "CA", 
        "INCIDENT_YEAR": "2003", 
        "AIRPORT": "SAN FRANCISCO INTL ARPT", 
        "INCIDENT_MONTH": "2", 
        "AIRPORT_ID": "KSFO", 
        "TIME": "125", 
        "INDEX_NR": "218086"
    }, 
    {
        "INCIDENT_DATE": "19-Feb-03", 
        "STATE": "NY", 
        "INCIDENT_YEAR": "2003", 
        "AIRPORT": "LAGUARDIA NY", 
        "INCIDENT_MONTH": "2", 
        "AIRPORT_ID": "KLGA", 
        "TIME": "", 
        "INDEX_NR": "214952"
    }, 
    {
        "INCIDENT_DATE": "19-Feb-03", 
        "STATE": "CA", 
        "INCIDENT_YEAR": "2003", 
        "AIRPORT": "GNOSS FIELD ARPT", 
        "INCIDENT_MONTH": "2", 
        "AIRPORT_ID": "KDVO", 
        "TIME": "900", 
        "INDEX_NR": "216198"
    }, 
    {
        "INCIDENT_DATE": "19-Feb-03", 
        "STATE": "FL", 
        "INCIDENT_YEAR": "2003", 
        "AIRPORT": "PAGE FIELD ARPT", 
        "INCIDENT_MONTH": "2", 
        "AIRPORT_ID": "KFMY", 
        "TIME": "1105", 
        "INDEX_NR": "217214"
    }, 
    {
        "INCIDENT_DATE": "19-Feb-03", 
        "STATE": "TN", 
        "INCIDENT_YEAR": "2003", 
        "AIRPORT": "MEMPHIS INTL", 
        "INCIDENT_MONTH": "2", 
        "AIRPORT_ID": "KMEM", 
        "TIME": "840", 
        "INDEX_NR": "217957"
    }, 
    {
        "INCIDENT_DATE": "19-Feb-03", 
        "STATE": "CT", 
        "INCIDENT_YEAR": "2003", 
        "AIRPORT": "WATERBURY-OXFORD ARPT", 
        "INCIDENT_MONTH": "2", 
        "AIRPORT_ID": "KOXC", 
        "TIME": "900", 
        "INDEX_NR": "218371"
    }, 
    {
        "INCIDENT_DATE": "19-Feb-03", 
        "STATE": "FL", 
        "INCIDENT_YEAR": "2003", 
        "AIRPORT": "FORT LAUDERDALE EXECUTIVE ARPT", 
        "INCIDENT_MONTH": "2", 
        "AIRPORT_ID": "KFXE", 
        "TIME": "2336", 
        "INDEX_NR": "219418"
    }, 
    {
        "INCIDENT_DATE": "20-Feb-03", 
        "STATE": "MS", 
        "INCIDENT_YEAR": "2003", 
        "AIRPORT": "KEY FLD", 
        "INCIDENT_MONTH": "2", 
        "AIRPORT_ID": "KMEI", 
        "TIME": "735", 
        "INDEX_NR": "4211"
    }, 
    {
        "INCIDENT_DATE": "20-Feb-03", 
        "STATE": "VA", 
        "INCIDENT_YEAR": "2003", 
        "AIRPORT": "RICHMOND INTL", 
        "INCIDENT_MONTH": "2", 
        "AIRPORT_ID": "KRIC", 
        "TIME": "1945", 
        "INDEX_NR": "7700"
    }, 
    {
        "INCIDENT_DATE": "20-Feb-03", 
        "STATE": "TX", 
        "INCIDENT_YEAR": "2003", 
        "AIRPORT": "SHEPPARD AIR FORCE BASE", 
        "INCIDENT_MONTH": "2", 
        "AIRPORT_ID": "KSPS", 
        "TIME": "800", 
        "INDEX_NR": "7701"
    }, 
    {
        "INCIDENT_DATE": "20-Feb-03", 
        "STATE": "MO", 
        "INCIDENT_YEAR": "2003", 
        "AIRPORT": "KANSAS CITY INTL", 
        "INCIDENT_MONTH": "2", 
        "AIRPORT_ID": "KMCI", 
        "TIME": "1350", 
        "INDEX_NR": "212519"
    }, 
    {
        "INCIDENT_DATE": "20-Feb-03", 
        "STATE": "NV", 
        "INCIDENT_YEAR": "2003", 
        "AIRPORT": "MCCARREN INTL", 
        "INCIDENT_MONTH": "2", 
        "AIRPORT_ID": "KLAS", 
        "TIME": "1915", 
        "INDEX_NR": "218245"
    }, 
    {
        "INCIDENT_DATE": "20-Feb-03", 
        "STATE": "NY", 
        "INCIDENT_YEAR": "2003", 
        "AIRPORT": "JOHN F KENNEDY INTL", 
        "INCIDENT_MONTH": "2", 
        "AIRPORT_ID": "KJFK", 
        "TIME": "", 
        "INDEX_NR": "219131"
    }, 
    {
        "INCIDENT_DATE": "20-Feb-03", 
        "STATE": "PI", 
        "INCIDENT_YEAR": "2003", 
        "AIRPORT": "HENDERSON FIELD", 
        "INCIDENT_MONTH": "2", 
        "AIRPORT_ID": "PMDY", 
        "TIME": "1530", 
        "INDEX_NR": "220762"
    }, 
    {
        "INCIDENT_DATE": "20-Feb-03", 
        "STATE": "CA", 
        "INCIDENT_YEAR": "2003", 
        "AIRPORT": "MINETA SAN JOSE INTL", 
        "INCIDENT_MONTH": "2", 
        "AIRPORT_ID": "KSJC", 
        "TIME": "", 
        "INDEX_NR": "220763"
    }, 
    {
        "INCIDENT_DATE": "20-Feb-03", 
        "STATE": "NY", 
        "INCIDENT_YEAR": "2003", 
        "AIRPORT": "LAGUARDIA NY", 
        "INCIDENT_MONTH": "2", 
        "AIRPORT_ID": "KLGA", 
        "TIME": "915", 
        "INDEX_NR": "221351"
    }, 
    {
        "INCIDENT_DATE": "20-Feb-03", 
        "STATE": "FL", 
        "INCIDENT_YEAR": "2003", 
        "AIRPORT": "ORLANDO INTL", 
        "INCIDENT_MONTH": "2", 
        "AIRPORT_ID": "KMCO", 
        "TIME": "", 
        "INDEX_NR": "221544"
    }, 
    {
        "INCIDENT_DATE": "20-Feb-03", 
        "STATE": "IL", 
        "INCIDENT_YEAR": "2003", 
        "AIRPORT": "CHICAGO O'HARE INTL ARPT", 
        "INCIDENT_MONTH": "2", 
        "AIRPORT_ID": "KORD", 
        "TIME": "1800", 
        "INDEX_NR": "222306"
    }, 
    {
        "INCIDENT_DATE": "20-Feb-03", 
        "STATE": "NY", 
        "INCIDENT_YEAR": "2003", 
        "AIRPORT": "LAGUARDIA NY", 
        "INCIDENT_MONTH": "2", 
        "AIRPORT_ID": "KLGA", 
        "TIME": "", 
        "INDEX_NR": "270125"
    }, 
    {
        "INCIDENT_DATE": "20-Feb-03", 
        "STATE": "NY", 
        "INCIDENT_YEAR": "2003", 
        "AIRPORT": "LAGUARDIA NY", 
        "INCIDENT_MONTH": "2", 
        "AIRPORT_ID": "KLGA", 
        "TIME": "", 
        "INDEX_NR": "270126"
    }, 
    {
        "INCIDENT_DATE": "21-Feb-03", 
        "STATE": "MA", 
        "INCIDENT_YEAR": "2003", 
        "AIRPORT": "WESTOVER ARB/METRO ARPT", 
        "INCIDENT_MONTH": "2", 
        "AIRPORT_ID": "KCEF", 
        "TIME": "1500", 
        "INDEX_NR": "7703"
    }, 
    {
        "INCIDENT_DATE": "21-Feb-03", 
        "STATE": "CT", 
        "INCIDENT_YEAR": "2003", 
        "AIRPORT": "BRADLEY INTL", 
        "INCIDENT_MONTH": "2", 
        "AIRPORT_ID": "KBDL", 
        "TIME": "", 
        "INDEX_NR": "217319"
    }, 
    {
        "INCIDENT_DATE": "21-Feb-03", 
        "STATE": "CO", 
        "INCIDENT_YEAR": "2003", 
        "AIRPORT": "YAMPA VALLEY", 
        "INCIDENT_MONTH": "2", 
        "AIRPORT_ID": "KHDN", 
        "TIME": "", 
        "INDEX_NR": "218726"
    }, 
    {
        "INCIDENT_DATE": "21-Feb-03", 
        "STATE": "N/A", 
        "INCIDENT_YEAR": "2003", 
        "AIRPORT": "LA AURORA", 
        "INCIDENT_MONTH": "2", 
        "AIRPORT_ID": "MGGT", 
        "TIME": "", 
        "INDEX_NR": "219291"
    }, 
    {
        "INCIDENT_DATE": "21-Feb-03", 
        "STATE": "LA", 
        "INCIDENT_YEAR": "2003", 
        "AIRPORT": "NEW ORLEANS INTL", 
        "INCIDENT_MONTH": "2", 
        "AIRPORT_ID": "KMSY", 
        "TIME": "1100", 
        "INDEX_NR": "219702"
    }, 
    {
        "INCIDENT_DATE": "21-Feb-03", 
        "STATE": "LA", 
        "INCIDENT_YEAR": "2003", 
        "AIRPORT": "NEW ORLEANS INTL", 
        "INCIDENT_MONTH": "2", 
        "AIRPORT_ID": "KMSY", 
        "TIME": "900", 
        "INDEX_NR": "220100"
    }, 
    {
        "INCIDENT_DATE": "21-Feb-03", 
        "STATE": "NY", 
        "INCIDENT_YEAR": "2003", 
        "AIRPORT": "JOHN F KENNEDY INTL", 
        "INCIDENT_MONTH": "2", 
        "AIRPORT_ID": "KJFK", 
        "TIME": "", 
        "INDEX_NR": "221180"
    }, 
    {
        "INCIDENT_DATE": "21-Feb-03", 
        "STATE": "OK", 
        "INCIDENT_YEAR": "2003", 
        "AIRPORT": "LAWTON-FORT SILL REGIONAL ARPT", 
        "INCIDENT_MONTH": "2", 
        "AIRPORT_ID": "KLAW", 
        "TIME": "", 
        "INDEX_NR": "221404"
    }, 
    {
        "INCIDENT_DATE": "21-Feb-03", 
        "STATE": "TX", 
        "INCIDENT_YEAR": "2003", 
        "AIRPORT": "AUSTIN-BERGSTROM INTL", 
        "INCIDENT_MONTH": "2", 
        "AIRPORT_ID": "KAUS", 
        "TIME": "", 
        "INDEX_NR": "223612"
    }, 
    {
        "INCIDENT_DATE": "21-Feb-03", 
        "STATE": "MO", 
        "INCIDENT_YEAR": "2003", 
        "AIRPORT": "SPRINGFIELD-BRANSON NATIONAL", 
        "INCIDENT_MONTH": "2", 
        "AIRPORT_ID": "KSGF", 
        "TIME": "", 
        "INDEX_NR": "223784"
    }, 
    {
        "INCIDENT_DATE": "22-Feb-03", 
        "STATE": "CA", 
        "INCIDENT_YEAR": "2003", 
        "AIRPORT": "SANTA BARBARA MUNICIPAL", 
        "INCIDENT_MONTH": "2", 
        "AIRPORT_ID": "KSBA", 
        "TIME": "2110", 
        "INDEX_NR": "214966"
    }, 
    {
        "INCIDENT_DATE": "22-Feb-03", 
        "STATE": "FL", 
        "INCIDENT_YEAR": "2003", 
        "AIRPORT": "SARASOTA-BRADENTON", 
        "INCIDENT_MONTH": "2", 
        "AIRPORT_ID": "KSRQ", 
        "TIME": "", 
        "INDEX_NR": "215864"
    }, 
    {
        "INCIDENT_DATE": "22-Feb-03", 
        "STATE": "DC", 
        "INCIDENT_YEAR": "2003", 
        "AIRPORT": "RONALD REAGAN WASHINGTON NATL", 
        "INCIDENT_MONTH": "2", 
        "AIRPORT_ID": "KDCA", 
        "TIME": "", 
        "INDEX_NR": "216273"
    }, 
    {
        "INCIDENT_DATE": "22-Feb-03", 
        "STATE": "FL", 
        "INCIDENT_YEAR": "2003", 
        "AIRPORT": "SARASOTA-BRADENTON", 
        "INCIDENT_MONTH": "2", 
        "AIRPORT_ID": "KSRQ", 
        "TIME": "1935", 
        "INDEX_NR": "217172"
    }, 
    {
        "INCIDENT_DATE": "22-Feb-03", 
        "STATE": "PI", 
        "INCIDENT_YEAR": "2003", 
        "AIRPORT": "HENDERSON FIELD", 
        "INCIDENT_MONTH": "2", 
        "AIRPORT_ID": "PMDY", 
        "TIME": "1925", 
        "INDEX_NR": "217680"
    }, 
    {
        "INCIDENT_DATE": "22-Feb-03", 
        "STATE": "AZ", 
        "INCIDENT_YEAR": "2003", 
        "AIRPORT": "PHOENIX SKY HARBOR", 
        "INCIDENT_MONTH": "2", 
        "AIRPORT_ID": "KPHX", 
        "TIME": "", 
        "INDEX_NR": "217797"
    }, 
    {
        "INCIDENT_DATE": "22-Feb-03", 
        "STATE": "MI", 
        "INCIDENT_YEAR": "2003", 
        "AIRPORT": "GERALD R FORD INTL", 
        "INCIDENT_MONTH": "2", 
        "AIRPORT_ID": "KGRR", 
        "TIME": "", 
        "INDEX_NR": "218430"
    }, 
    {
        "INCIDENT_DATE": "22-Feb-03", 
        "STATE": "DC", 
        "INCIDENT_YEAR": "2003", 
        "AIRPORT": "RONALD REAGAN WASHINGTON NATL", 
        "INCIDENT_MONTH": "2", 
        "AIRPORT_ID": "KDCA", 
        "TIME": "1400", 
        "INDEX_NR": "220716"
    }, 
    {
        "INCIDENT_DATE": "22-Feb-03", 
        "STATE": "TX", 
        "INCIDENT_YEAR": "2003", 
        "AIRPORT": "DALLAS/FORT WORTH INTL ARPT", 
        "INCIDENT_MONTH": "2", 
        "AIRPORT_ID": "KDFW", 
        "TIME": "", 
        "INDEX_NR": "221042"
    }, 
    {
        "INCIDENT_DATE": "23-Feb-03", 
        "STATE": "TX", 
        "INCIDENT_YEAR": "2003", 
        "AIRPORT": "AUSTIN-BERGSTROM INTL", 
        "INCIDENT_MONTH": "2", 
        "AIRPORT_ID": "KAUS", 
        "TIME": "", 
        "INDEX_NR": "215505"
    }, 
    {
        "INCIDENT_DATE": "23-Feb-03", 
        "STATE": "CA", 
        "INCIDENT_YEAR": "2003", 
        "AIRPORT": "SAN FRANCISCO INTL ARPT", 
        "INCIDENT_MONTH": "2", 
        "AIRPORT_ID": "KSFO", 
        "TIME": "", 
        "INDEX_NR": "216425"
    }, 
    {
        "INCIDENT_DATE": "23-Feb-03", 
        "STATE": "CA", 
        "INCIDENT_YEAR": "2003", 
        "AIRPORT": "LOS ANGELES INTL", 
        "INCIDENT_MONTH": "2", 
        "AIRPORT_ID": "KLAX", 
        "TIME": "", 
        "INDEX_NR": "216490"
    }, 
    {
        "INCIDENT_DATE": "23-Feb-03", 
        "STATE": "PA", 
        "INCIDENT_YEAR": "2003", 
        "AIRPORT": "WILKES-BARRE/SCRANTON INTL", 
        "INCIDENT_MONTH": "2", 
        "AIRPORT_ID": "KAVP", 
        "TIME": "835", 
        "INDEX_NR": "217358"
    }, 
    {
        "INCIDENT_DATE": "23-Feb-03", 
        "STATE": "PA", 
        "INCIDENT_YEAR": "2003", 
        "AIRPORT": "LEHIGH VALLEY INTL", 
        "INCIDENT_MONTH": "2", 
        "AIRPORT_ID": "KABE", 
        "TIME": "", 
        "INDEX_NR": "217591"
    }, 
    {
        "INCIDENT_DATE": "23-Feb-03", 
        "STATE": "TN", 
        "INCIDENT_YEAR": "2003", 
        "AIRPORT": "MEMPHIS INTL", 
        "INCIDENT_MONTH": "2", 
        "AIRPORT_ID": "KMEM", 
        "TIME": "", 
        "INDEX_NR": "218108"
    }, 
    {
        "INCIDENT_DATE": "23-Feb-03", 
        "STATE": "N/A", 
        "INCIDENT_YEAR": "2003", 
        "AIRPORT": "UNKNOWN", 
        "INCIDENT_MONTH": "2", 
        "AIRPORT_ID": "UNK", 
        "TIME": "", 
        "INDEX_NR": "221225"
    }, 
    {
        "INCIDENT_DATE": "23-Feb-03", 
        "STATE": "WA", 
        "INCIDENT_YEAR": "2003", 
        "AIRPORT": "SEATTLE-TACOMA INTL", 
        "INCIDENT_MONTH": "2", 
        "AIRPORT_ID": "KSEA", 
        "TIME": "", 
        "INDEX_NR": "222777"
    }, 
    {
        "INCIDENT_DATE": "23-Feb-03", 
        "STATE": "NC", 
        "INCIDENT_YEAR": "2003", 
        "AIRPORT": "RALEIGH-DURHAM INTL", 
        "INCIDENT_MONTH": "2", 
        "AIRPORT_ID": "KRDU", 
        "TIME": "733", 
        "INDEX_NR": "222939"
    }, 
    {
        "INCIDENT_DATE": "23-Feb-03", 
        "STATE": "WA", 
        "INCIDENT_YEAR": "2003", 
        "AIRPORT": "SEATTLE-TACOMA INTL", 
        "INCIDENT_MONTH": "2", 
        "AIRPORT_ID": "KSEA", 
        "TIME": "", 
        "INDEX_NR": "226764"
    }, 
    {
        "INCIDENT_DATE": "24-Feb-03", 
        "STATE": "FL", 
        "INCIDENT_YEAR": "2003", 
        "AIRPORT": "EGLIN AFB/NW FLORIDA REGIONAL ARPT", 
        "INCIDENT_MONTH": "2", 
        "AIRPORT_ID": "KVPS", 
        "TIME": "", 
        "INDEX_NR": "6889"
    }, 
    {
        "INCIDENT_DATE": "24-Feb-03", 
        "STATE": "OR", 
        "INCIDENT_YEAR": "2003", 
        "AIRPORT": "PORTLAND INTL (OR)", 
        "INCIDENT_MONTH": "2", 
        "AIRPORT_ID": "KPDX", 
        "TIME": "1718", 
        "INDEX_NR": "213303"
    }, 
    {
        "INCIDENT_DATE": "24-Feb-03", 
        "STATE": "N/A", 
        "INCIDENT_YEAR": "2003", 
        "AIRPORT": "UNKNOWN", 
        "INCIDENT_MONTH": "2", 
        "AIRPORT_ID": "UNK", 
        "TIME": "", 
        "INDEX_NR": "214832"
    }, 
    {
        "INCIDENT_DATE": "24-Feb-03", 
        "STATE": "GA", 
        "INCIDENT_YEAR": "2003", 
        "AIRPORT": "ATLANTA INTL", 
        "INCIDENT_MONTH": "2", 
        "AIRPORT_ID": "KATL", 
        "TIME": "1730", 
        "INDEX_NR": "216033"
    }, 
    {
        "INCIDENT_DATE": "24-Feb-03", 
        "STATE": "N/A", 
        "INCIDENT_YEAR": "2003", 
        "AIRPORT": "UNKNOWN", 
        "INCIDENT_MONTH": "2", 
        "AIRPORT_ID": "UNK", 
        "TIME": "", 
        "INDEX_NR": "216652"
    }, 
    {
        "INCIDENT_DATE": "24-Feb-03", 
        "STATE": "AZ", 
        "INCIDENT_YEAR": "2003", 
        "AIRPORT": "PHOENIX SKY HARBOR", 
        "INCIDENT_MONTH": "2", 
        "AIRPORT_ID": "KPHX", 
        "TIME": "", 
        "INDEX_NR": "217495"
    }, 
    {
        "INCIDENT_DATE": "24-Feb-03", 
        "STATE": "DC", 
        "INCIDENT_YEAR": "2003", 
        "AIRPORT": "RONALD REAGAN WASHINGTON NATL", 
        "INCIDENT_MONTH": "2", 
        "AIRPORT_ID": "KDCA", 
        "TIME": "", 
        "INDEX_NR": "218789"
    }, 
    {
        "INCIDENT_DATE": "24-Feb-03", 
        "STATE": "FL", 
        "INCIDENT_YEAR": "2003", 
        "AIRPORT": "ORLANDO INTL", 
        "INCIDENT_MONTH": "2", 
        "AIRPORT_ID": "KMCO", 
        "TIME": "", 
        "INDEX_NR": "218815"
    }, 
    {
        "INCIDENT_DATE": "24-Feb-03", 
        "STATE": "AL", 
        "INCIDENT_YEAR": "2003", 
        "AIRPORT": "BIRMINGHAM-SHUTTLESWORTH INTL", 
        "INCIDENT_MONTH": "2", 
        "AIRPORT_ID": "KBHM", 
        "TIME": "20", 
        "INDEX_NR": "219393"
    }, 
    {
        "INCIDENT_DATE": "24-Feb-03", 
        "STATE": "CA", 
        "INCIDENT_YEAR": "2003", 
        "AIRPORT": "SAN FRANCISCO INTL ARPT", 
        "INCIDENT_MONTH": "2", 
        "AIRPORT_ID": "KSFO", 
        "TIME": "", 
        "INDEX_NR": "219394"
    }, 
    {
        "INCIDENT_DATE": "24-Feb-03", 
        "STATE": "IL", 
        "INCIDENT_YEAR": "2003", 
        "AIRPORT": "CHICAGO O'HARE INTL ARPT", 
        "INCIDENT_MONTH": "2", 
        "AIRPORT_ID": "KORD", 
        "TIME": "", 
        "INDEX_NR": "220531"
    }, 
    {
        "INCIDENT_DATE": "24-Feb-03", 
        "STATE": "NY", 
        "INCIDENT_YEAR": "2003", 
        "AIRPORT": "LAGUARDIA NY", 
        "INCIDENT_MONTH": "2", 
        "AIRPORT_ID": "KLGA", 
        "TIME": "", 
        "INDEX_NR": "270127"
    }, 
    {
        "INCIDENT_DATE": "25-Feb-03", 
        "STATE": "NH", 
        "INCIDENT_YEAR": "2003", 
        "AIRPORT": "PEASE INTL TRADEPORT", 
        "INCIDENT_MONTH": "2", 
        "AIRPORT_ID": "KPSM", 
        "TIME": "", 
        "INDEX_NR": "218752"
    }, 
    {
        "INCIDENT_DATE": "25-Feb-03", 
        "STATE": "FL", 
        "INCIDENT_YEAR": "2003", 
        "AIRPORT": "PALM BEACH INTL", 
        "INCIDENT_MONTH": "2", 
        "AIRPORT_ID": "KPBI", 
        "TIME": "", 
        "INDEX_NR": "219734"
    }, 
    {
        "INCIDENT_DATE": "26-Feb-03", 
        "STATE": "OR", 
        "INCIDENT_YEAR": "2003", 
        "AIRPORT": "PORTLAND INTL (OR)", 
        "INCIDENT_MONTH": "2", 
        "AIRPORT_ID": "KPDX", 
        "TIME": "", 
        "INDEX_NR": "217069"
    }, 
    {
        "INCIDENT_DATE": "26-Feb-03", 
        "STATE": "N/A", 
        "INCIDENT_YEAR": "2003", 
        "AIRPORT": "UNKNOWN", 
        "INCIDENT_MONTH": "2", 
        "AIRPORT_ID": "UNK", 
        "TIME": "1445", 
        "INDEX_NR": "218674"
    }, 
    {
        "INCIDENT_DATE": "26-Feb-03", 
        "STATE": "CO", 
        "INCIDENT_YEAR": "2003", 
        "AIRPORT": "YAMPA VALLEY", 
        "INCIDENT_MONTH": "2", 
        "AIRPORT_ID": "KHDN", 
        "TIME": "1400", 
        "INDEX_NR": "218979"
    }, 
    {
        "INCIDENT_DATE": "26-Feb-03", 
        "STATE": "CA", 
        "INCIDENT_YEAR": "2003", 
        "AIRPORT": "SACRAMENTO INTL", 
        "INCIDENT_MONTH": "2", 
        "AIRPORT_ID": "KSMF", 
        "TIME": "1245", 
        "INDEX_NR": "219321"
    }, 
    {
        "INCIDENT_DATE": "26-Feb-03", 
        "STATE": "NY", 
        "INCIDENT_YEAR": "2003", 
        "AIRPORT": "JOHN F KENNEDY INTL", 
        "INCIDENT_MONTH": "2", 
        "AIRPORT_ID": "KJFK", 
        "TIME": "", 
        "INDEX_NR": "219682"
    }, 
    {
        "INCIDENT_DATE": "27-Feb-03", 
        "STATE": "FL", 
        "INCIDENT_YEAR": "2003", 
        "AIRPORT": "MIAMI INTL", 
        "INCIDENT_MONTH": "2", 
        "AIRPORT_ID": "KMIA", 
        "TIME": "", 
        "INDEX_NR": "214856"
    }, 
    {
        "INCIDENT_DATE": "27-Feb-03", 
        "STATE": "AZ", 
        "INCIDENT_YEAR": "2003", 
        "AIRPORT": "TUCSON INTL", 
        "INCIDENT_MONTH": "2", 
        "AIRPORT_ID": "KTUS", 
        "TIME": "", 
        "INDEX_NR": "215234"
    }, 
    {
        "INCIDENT_DATE": "27-Feb-03", 
        "STATE": "N/A", 
        "INCIDENT_YEAR": "2003", 
        "AIRPORT": "UNKNOWN", 
        "INCIDENT_MONTH": "2", 
        "AIRPORT_ID": "UNK", 
        "TIME": "", 
        "INDEX_NR": "216364"
    }, 
    {
        "INCIDENT_DATE": "27-Feb-03", 
        "STATE": "CA", 
        "INCIDENT_YEAR": "2003", 
        "AIRPORT": "LOS ANGELES INTL", 
        "INCIDENT_MONTH": "2", 
        "AIRPORT_ID": "KLAX", 
        "TIME": "", 
        "INDEX_NR": "217765"
    }, 
    {
        "INCIDENT_DATE": "27-Feb-03", 
        "STATE": "IL", 
        "INCIDENT_YEAR": "2003", 
        "AIRPORT": "CHICAGO O'HARE INTL ARPT", 
        "INCIDENT_MONTH": "2", 
        "AIRPORT_ID": "KORD", 
        "TIME": "", 
        "INDEX_NR": "219637"
    }, 
    {
        "INCIDENT_DATE": "27-Feb-03", 
        "STATE": "FL", 
        "INCIDENT_YEAR": "2003", 
        "AIRPORT": "DAYTONA BEACH INTL", 
        "INCIDENT_MONTH": "2", 
        "AIRPORT_ID": "KDAB", 
        "TIME": "1153", 
        "INDEX_NR": "221828"
    }, 
    {
        "INCIDENT_DATE": "27-Feb-03", 
        "STATE": "AL", 
        "INCIDENT_YEAR": "2003", 
        "AIRPORT": "SOUTH ALABAMA REGIONAL ARPT", 
        "INCIDENT_MONTH": "2", 
        "AIRPORT_ID": "79J", 
        "TIME": "", 
        "INDEX_NR": "222315"
    }, 
    {
        "INCIDENT_DATE": "27-Feb-03", 
        "STATE": "OR", 
        "INCIDENT_YEAR": "2003", 
        "AIRPORT": "PORTLAND INTL (OR)", 
        "INCIDENT_MONTH": "2", 
        "AIRPORT_ID": "KPDX", 
        "TIME": "935", 
        "INDEX_NR": "223893"
    }, 
    {
        "INCIDENT_DATE": "27-Feb-03", 
        "STATE": "UT", 
        "INCIDENT_YEAR": "2003", 
        "AIRPORT": "SALT LAKE CITY INTL", 
        "INCIDENT_MONTH": "2", 
        "AIRPORT_ID": "KSLC", 
        "TIME": "740", 
        "INDEX_NR": "223894"
    }, 
    {
        "INCIDENT_DATE": "27-Feb-03", 
        "STATE": "NJ", 
        "INCIDENT_YEAR": "2003", 
        "AIRPORT": "NEWARK LIBERTY INTL ARPT", 
        "INCIDENT_MONTH": "2", 
        "AIRPORT_ID": "KEWR", 
        "TIME": "", 
        "INDEX_NR": "223895"
    }, 
    {
        "INCIDENT_DATE": "28-Feb-03", 
        "STATE": "AR", 
        "INCIDENT_YEAR": "2003", 
        "AIRPORT": "FORT SMITH MUNICIPAL ARPT", 
        "INCIDENT_MONTH": "2", 
        "AIRPORT_ID": "KFSM", 
        "TIME": "1506", 
        "INDEX_NR": "5502"
    }, 
    {
        "INCIDENT_DATE": "28-Feb-03", 
        "STATE": "IL", 
        "INCIDENT_YEAR": "2003", 
        "AIRPORT": "CHICAGO O'HARE INTL ARPT", 
        "INCIDENT_MONTH": "2", 
        "AIRPORT_ID": "KORD", 
        "TIME": "1219", 
        "INDEX_NR": "215712"
    }, 
    {
        "INCIDENT_DATE": "28-Feb-03", 
        "STATE": "DC", 
        "INCIDENT_YEAR": "2003", 
        "AIRPORT": "RONALD REAGAN WASHINGTON NATL", 
        "INCIDENT_MONTH": "2", 
        "AIRPORT_ID": "KDCA", 
        "TIME": "", 
        "INDEX_NR": "221067"
    }, 
    {
        "INCIDENT_DATE": "28-Feb-03", 
        "STATE": "IL", 
        "INCIDENT_YEAR": "2003", 
        "AIRPORT": "CHICAGO MIDWAY INTL ARPT", 
        "INCIDENT_MONTH": "2", 
        "AIRPORT_ID": "KMDW", 
        "TIME": "", 
        "INDEX_NR": "224520"
    }
]